aws_flask_lambda/aws_flask_lambda.py
aws_flask_lambda-0.1.2.dist-info/METADATA
aws_flask_lambda-0.1.2.dist-info/WHEEL
aws_flask_lambda-0.1.2.dist-info/top_level.txt
aws_flask_lambda-0.1.2.dist-info/RECORD
