Metadata-Version: 2.1
Name: aws-flask-lambda
Version: 0.1.2
Summary: Library to run applications on AWS Lambda Function using Flask
Home-page: UNKNOWN
Author: Seven Clouds Technologies
Author-email: admin@seventechnologies.cloud
License: UNKNOWN
Platform: UNKNOWN
Classifier: Programming Language :: Python :: 3.8
Classifier: License :: OSI Approved :: MIT License
Classifier: Operating System :: OS Independent
Requires-Dist: Flask (==2.0.2)
Requires-Dist: werkzeug (==2.0.2)
